Workbook

Sheet RO_0
E1: =+E4*$K$1 -> 123095.7 | F1: =+F4*$K$1 -> 139144.84 | G1: =+G4*$K$1 -> 223303.85 | H1: =+H4*$K$1 -> 464640.51 | I1: =+J1-SUM(E1:H1) -> 219963.09 | J1: 1170148 | K1: =+J1/J4 -> 1.0391155
A2: Concept | B2: Current Month (To go-1) | C2: Current Month Real | D2: Cumulative to date | E2: To go Month 1 | F2: To go Month 2 | G2: To go Month 3 | H2: To go Month 4 | I2: To go Month 5 | J2: Current Remaining | K2: At completion Current | L2: At completion Previous | M2: At completion Target
A3: EARN REVENUE | E3: =SUM(E4:E9) -> 132677.44 | F3: =SUM(F4:F9) -> 149975.84 | G3: =SUM(G4:G9) -> 240685.76 | H3: =SUM(H4:H9) -> 500808 | I3: =SUM(I4:I9) -> 237084.96 | J3: =SUM(E3:I3) -> 1261232 | K3: =+J3+D3 -> 1261232 | M3: 1261232
A4: Earn value Plus work in progrees | E4: 118462 | F4: 133907 | G4: 214898 | H4: 447150 | I4: 211683 | J4: =SUM(E4:I4) -> 1126100 | K4: =+J4+D4 -> 1126100 | M4: 1126100
A5: Profit + overheads (12%) | E5: =+E4*0.12 -> 14215.44 | F5: =+F4*0.12 -> 16068.84 | G5: =+G4*0.12 -> 25787.76 | H5: =+H4*0.12 -> 53658 | I5: =+I4*0.12 -> 25401.96 | J5: =SUM(E5:I5) -> 135132 | K5: =+J5+D5 -> 135132 | M5: 135132
A6: Additional Claims | J6: =SUM(F6:I6) -> 0 | K6: =+J6+D6 -> 0 | M6: 0
A7: Claims to other projects | J7: =SUM(F7:I7) -> 0 | K7: =+J7+D7 -> 0 | M7: 0
A8: Claims to third parties | J8: =SUM(F8:I8) -> 0 | K8: =+J8+D8 -> 0 | M8: 0
A9: Claims to subcontractos | J9: =SUM(F9:I9) -> 0 | K9: =+J9+D9 -> 0 | M9: 0
A10: COST | E10: =SUM(E11:E16) -> 131095.7 | F10: =SUM(F11:F16) -> 147144.84 | G10: =SUM(G11:G16) -> 231303.85 | H10: =SUM(H11:H16) -> 472640.51 | I10: =SUM(I11:I16) -> 227963.09 | J10: =SUM(J11:J16) -> 1210148 | K10: =SUM(K11:K16) -> 1210148 | M10: 1210148 | S10: =+SUM(E10:I10) -> 1210148
A11: Materials | E11: =+N11*E$1 -> 98476.563 | F11: =+O11*F$1 -> 41743.453 | G11: =+P11*G$1 -> 89321.54 | H11: =+Q11*H$1 -> 185856.2 | I11: =+R11*I$1 -> 87985.237 | J11: =SUM(E11:I11) -> 503383 | K11: =+J11+D11 -> 503383 | M11: 503383 | N11: 0.8 | O11: 0.3 | P11: 0.4 | Q11: 0.4 | R11: 0.4 | S11: =+SUM(E11:I14) -> 1170148
A12: Labor | E12: =+N12*E$1 -> 0 | F12: =+O12*F$1 -> 83486.906 | G12: =+P12*G$1 -> 111651.92 | H12: =+Q12*H$1 -> 232320.25 | I12: =+R12*I$1 -> 109981.55 | J12: =SUM(E12:I12) -> 537440.63 | K12: =+J12+D12 -> 537440.63 | M12: 537440.63 | O12: 0.6 | P12: 0.5 | Q12: 0.5 | R12: 0.5
A13: Subcontractor | E13: =+N13*E$1 -> 0 | F13: =+O13*F$1 -> 0 | G13: =+P13*G$1 -> 0 | H13: =+Q13*H$1 -> 0 | I13: =+R13*I$1 -> 0 | J13: =SUM(E13:I13) -> 0 | K13: =+J13+D13 -> 0 | M13: 0
A14: Plant | E14: =+N14*E$1 -> 24619.141 | F14: =+O14*F$1 -> 13914.484 | G14: =+P14*G$1 -> 22330.385 | H14: =+Q14*H$1 -> 46464.051 | I14: =+R14*I$1 -> 21996.309 | J14: =SUM(E14:I14) -> 129324.37 | K14: =+J14+D14 -> 129324.37 | M14: 129324.37 | N14: 0.2 | O14: 0.1 | P14: 0.1 | Q14: 0.1 | R14: 0.1
A15: Overhead and indirects | E15: 8000 | F15: 8000 | G15: 8000 | H15: 8000 | I15: 8000 | J15: =SUM(E15:I15) -> 40000 | K15: =+J15+D15 -> 40000 | M15: 40000
J16: =SUM(E16:I16) -> 0 | K16: =+J16+D16 -> 0 | M16: 0
A17: Margen ('Earn revenue - Cost) | E17: =E3-E10 -> 1581.7359 | F17: =F3-F10 -> 2830.9965 | G17: =G3-G10 -> 9381.9105 | H17: =H3-H10 -> 28167.49 | I17: =I3-I10 -> 9121.8669 | J17: =J3-J10 -> 51084 | K17: =K3-K10 -> 51084 | M17: =M3-M10 -> 51084 | S17: =+SUM(E17:I17) -> 51084
A18: %Margen (Margen / Earn Revenue) | E18: =ROUND(E17/E3,2) -> 0.01 | F18: =ROUND(F17/F3,2) -> 0.02 | G18: =ROUND(G17/G3,2) -> 0.04 | H18: =ROUND(H17/H3,2) -> 0.06 | I18: =ROUND(I17/I3,2) -> 0.04 | J18: =ROUND(J17/J3,2) -> 0.04 | K18: =ROUND(K17/K3,2) -> 0.04 | M18: =ROUND(M17/M3,2) -> 0.04
A22: Concept | B22: Current Month (To go-1) | C22: Current Month Real | D22: Cumulative to date | F22: To go Month 2 | G22: To go Month 3 | H22: To go Month 4 | I22: To go Month 5 | J22: Current Remaining | K22: At completion Current | L22: At completion Previous | M22: At completion Target
A23: EARN REVENUE | B23: =SUM(B24:B29) -> 132677.44 | C23: =SUM(C24:C29) -> 133160 | D23: =+C23 -> 133160 | F23: =SUM(F24:F29) -> 150493.28 | G23: =SUM(G24:G29) -> 240685.76 | H23: =SUM(H24:H29) -> 500808 | I23: =SUM(I24:I29) -> 237084.96 | J23: =SUM(F23:I23) -> 1129072 | K23: =+J23+D23 -> 1262232 | M23: 1261232
A24: Earn value | B24: 118462 | C24: 118000 | D24: =+C24 -> 118000 | F24: =+F4+B24-C24 -> 134369 | G24: 214898 | H24: 447150 | I24: 211683 | J24: =SUM(F24:I24) -> 1008100 | K24: =+J24+D24 -> 1126100 | M24: 1126100
A25: Profit + overheads (12%) | B25: =+B24*0.12 -> 14215.44 | C25: =+C24*0.12 -> 14160 | D25: =+D24*0.12 -> 14160 | F25: =+F24*0.12 -> 16124.28 | G25: =+G24*0.12 -> 25787.76 | H25: =+H24*0.12 -> 53658 | I25: =+I24*0.12 -> 25401.96 | J25: =SUM(F25:I25) -> 120972 | K25: =+J25+D25 -> 135132 | M25: 135132
A26: Additional Claims | C26: 1000 | D26: =+C26 -> 1000 | J26: =SUM(F26:I26) -> 0 | K26: =+J26+D26 -> 1000 | M26: 0
A27: Claims to other projects | J27: =SUM(F27:I27) -> 0 | K27: =+J27+D27 -> 0 | M27: 0
A28: Claims to third parties | J28: =SUM(F28:I28) -> 0 | K28: =+J28+D28 -> 0 | M28: 0
A29: Claims to subcontractos | J29: =SUM(F29:I29) -> 0 | K29: =+J29+D29 -> 0 | M29: 0
A30: COST | B30: =SUM(B31:B35) -> 131095.7 | C30: =SUM(C31:C35) -> 135440 | D30: =+C30 -> 135440 | F30: =SUM(F31:F36) -> 147144.84 | G30: =SUM(G31:G36) -> 231303.85 | H30: =SUM(H31:H36) -> 472640.51 | I30: =SUM(I31:I36) -> 227963.09 | J30: =SUM(J31:J36) -> 1079052.3 | K30: =SUM(K31:K36) -> 1214492.3 | M30: =SUM(M31:M36) -> 1210148
A31: Materials | B31: 98476.563 | C31: 97000 | D31: =+C31 -> 97000 | F31: 41743.453 | G31: 89321.54 | H31: 185856.2 | I31: 87985.237 | J31: =SUM(F31:I31) -> 404906.43 | K31: =+J31+D31 -> 501906.43 | M31: 503383
A32: Labor | B32: 0 | D32: =+C32 -> 0 | F32: 83486.906 | G32: 111651.92 | H32: 232320.25 | I32: 109981.55 | J32: =SUM(F32:I32) -> 537440.63 | K32: =+J32+D32 -> 537440.63 | M32: 537440.63
A33: Subcontractor | B33: 0 | D33: =+C33 -> 0 | F33: 0 | G33: 0 | H33: 0 | I33: 0 | J33: =SUM(F33:I33) -> 0 | K33: =+J33+D33 -> 0 | M33: 0
A34: Plant | B34: 24619.141 | C34: 30440 | D34: =+C34 -> 30440 | F34: 13914.484 | G34: 22330.385 | H34: 46464.051 | I34: 21996.309 | J34: =SUM(F34:I34) -> 104705.23 | K34: =+J34+D34 -> 135145.23 | M34: 129324.37
A35: Overhead and indirects | B35: 8000 | C35: 8000 | D35: =+C35 -> 8000 | F35: 8000 | G35: 8000 | H35: 8000 | I35: 8000 | J35: =SUM(F35:I35) -> 32000 | K35: =+J35+D35 -> 40000 | M35: 40000
J36: =SUM(F36:I36) -> 0 | K36: =+J36+D36 -> 0 | M36: 0
A37: Profit ('Earn revenue - Cost) | C37: =C23-C30 -> -2280 | F37: =F23-F30 -> 3348.4365 | G37: =G23-G30 -> 9381.9105 | H37: =H23-H30 -> 28167.49 | I37: =I23-I30 -> 9121.8669 | J37: =J23-J30 -> 50019.704 | K37: =K23-K30 -> 47739.704 | M37: =M23-M30 -> 51084
A38: %Profit (Profit / Earn Revenue) | C38: =ROUND(C37/C23,2) -> -0.02 | F38: =ROUND(F37/F23,2) -> 0.02 | G38: =ROUND(G37/G23,2) -> 0.04 | H38: =ROUND(H37/H23,2) -> 0.06 | I38: =ROUND(I37/I23,2) -> 0.04 | J38: =ROUND(J37/J23,2) -> 0.04 | K38: =ROUND(K37/K23,2) -> 0.04 | M38: =ROUND(M37/M23,2) -> 0.04

Sheet Cost category
B2: Cost Category | C2: Description
B3: Labour
B4: Material
B5: Equipment

Sheet CBSS
B2: Code | C2: Cost account | D2: Description
B3: C-100 | C3: Cost account 1
B4: C-200 | C4: Cost account 2
B5: C-300 | C5: Cost account 3
B6: C-400 | C6: Cost account 4

Sheet Budget
D3: BUDGET
B4: Activity | C4: Activity title | D4: Cantidad | E4: Price | F4: Cost | G4: Duration
B5: WBS 1 | C5: PROVISIONALES
B6: Activity 1 | C6: CARTEL PARA LA OBRA DE 3.60X2.40M. | D6: 1 | E6: 80000 | F6: =D6*E6 -> 80000 | G6: 15
B7: Activity 2 | C7: ALQUILER DE VIVIENDA PARA OFICINA Y ALMACÉN | D7: 1 | E7: 50000 | F7: =D7*E7 -> 50000 | G7: 10
B8: Activity 3 | C8: MOVILIZACION Y DESMOVILIZACION DE EQUIPO_x000D_ | D8: 1 | E8: 50000 | F8: =D8*E8 -> 50000 | G8: 10
B9: WBS 2 | C9: OBRAS PRELIMINARES | G9: 20
B10: Activity 4 | C10: LIMPIEZA DE TERRENO MANUAL | D10: 2400 | E10: 14 | F10: =D10*E10 -> 33600 | G10: 10
B11: Activity 5 | C11: TRAZO Y REPLANTEO INICIALES DEL PROYECTO | D11: 6000 | E11: 14 | F11: =D11*E11 -> 84000 | G11: 10
B12: WBS 3 | C12: MOVIMIENTO DE TIERRAS | G12: 50
B13: Activity 6 | C13: EXCAVACION MASIVA CON MAQUINA | D13: 14000 | E13: 12 | F13: =D13*E13 -> 168000 | G13: 15
B14: Activity 7 | C14: RELLENO COMPACTADO CON MATERIAL PROPIO | D14: 8000 | E14: 35 | F14: =D14*E14 -> 280000 | G14: 10
B15: Activity 8 | C15: RELLENO COMPACTADO CON MATERIAL DE PRESTAMO | D15: 750 | E15: 70 | F15: =D15*E15 -> 52500 | G15: 15
B16: WBS 4 | C16: CONCRETO SIMPLE | G16: 20
B17: WBS 4.1 | C17: SOLADO PARA ZAPATAS | G17: 5
B18: Activity 9 | C18: SOLADO DE CONCRETO PARA ZAPATAS MEZCLA 1:12 (e=2") | D18: 200 | E18: 25 | F18: =D18*E18 -> 5000 | G18: 5
B19: WBS 4.1 | C19: MUROS DE CONTENCION | G19: 15
B20: Activity 10 | C20: ENCOFRADO Y DESENCOFRADO NORMAL PARA MUROS DE CONTENCION_x000D_ | D20: 5000 | E20: 45 | F20: =D20*E20 -> 225000 | G20: 10
B21: Activity 11 | C21: ENCOFRADO Y DESENCOFRADO NORMAL EN ZAPATAS DE MURO | D21: 750 | E21: 50 | F21: =D21*E21 -> 37500 | G21: 15
B22: Activity 12 | C22: CONCRETO CICLOPEO 30%PM PARA MUROS f'c=140 kg/m2 | D22: 1100 | E22: 55 | F22: =D22*E22 -> 60500 | G22: 5
F24: =SUM(F6:F22) -> 1126100

Sheet Budget Cost
B1: BUDGET | F1: Code Of Accounts | H1: Cost per Unit | K1: Cost per Unit | N1: Cost per Quantity | P1: Activity Name | Q1: Planned Start | R1: Planned Finish | S1: Progress | W1: Cost planned due to the actual progress
A2: Activity | B2: Qty | C2: Price | D2: Cost | E2: Code | F2: Cost account | G2: Unit pctg Labour | H2: Unit pctg Mat | I2: Unit pctg Eq. | J2: unit cost Labour | K2: unit cost Mat | L2: unit cost Eq. | M2: subtotal Labour | N2: subtotal Mat | O2: subtotal Eq. | P2: Activity Name | Q2: Planned Start | R2: Planned Finish | S2: % | T2: EV | U2: Code | V2: Labour | W2: Mat | X2: Eq.
A3: WBS 1 | P3: PROVISIONALES
A4: Activity 1 | B4: 1 | C4: 80000 | D4: =B4*C4 -> 80000 | E4: C-100 | F4: Cost account 1 | G4: 0 | H4: 1 | I4: =1-H4-G4 -> 0 | J4: =+G4*$C4 -> 0 | K4: =+H4*$C4 -> 80000 | L4: =+I4*$C4 -> 0 | M4: =J4*$B4 -> 0 | N4: =K4*$B4 -> 80000 | O4: =L4*$B4 -> 0 | P4: CARTEL PARA LA OBRA DE 3.60X2.40M. | Q4: 46148 | R4: 46168 | S4: 1 | T4: =S4*D4 -> 80000 | U4: C-100 | V4: =M4*$S4 -> 0 | W4: =N4*$S4 -> 80000 | X4: =O4*$S4 -> 0
A5: Activity 2 | B5: 1 | C5: 50000 | D5: =B5*C5 -> 50000 | E5: C-100 | F5: Cost account 1 | G5: 0 | H5: 1 | I5: =1-H5-G5 -> 0 | J5: =+G5*$C5 -> 0 | K5: =+H5*$C5 -> 50000 | L5: =+I5*$C5 -> 0 | M5: =J5*$B5 -> 0 | N5: =K5*$B5 -> 50000 | O5: =L5*$B5 -> 0 | P5: ALQUILER DE VIVIENDA PARA OFICINA Y ALMACÉN | Q5: 46169 | R5: 46182 | S5: 0.38 | T5: =S5*D5 -> 19000 | U5: C-100 | V5: =M5*$S5 -> 0 | W5: =N5*$S5 -> 19000 | X5: =O5*$S5 -> 0
A6: Activity 3 | B6: 1 | C6: 50000 | D6: =B6*C6 -> 50000 | E6: C-100 | F6: Cost account 1 | G6: 0 | H6: 0 | I6: =1-H6-G6 -> 1 | J6: =+G6*$C6 -> 0 | K6: =+H6*$C6 -> 0 | L6: =+I6*$C6 -> 50000 | M6: =J6*$B6 -> 0 | N6: =K6*$B6 -> 0 | O6: =L6*$B6 -> 50000 | P6: MOVILIZACION Y DESMOVILIZACION DE EQUIPO_x000D_ | Q6: 46169 | R6: 46182 | S6: 0.38 | T6: =S6*D6 -> 19000 | U6: C-100 | V6: =M6*$S6 -> 0 | W6: =N6*$S6 -> 0 | X6: =O6*$S6 -> 19000
A7: WBS 2 | J7: =+G7*$C7 -> 0 | K7: =+H7*$C7 -> 0 | L7: =+I7*$C7 -> 0 | P7: OBRAS PRELIMINARES
A8: Activity 4 | B8: 2400 | C8: 14 | D8: =B8*C8 -> 33600 | E8: C-100 | F8: Cost account 1 | G8: 0.97035868 | H8: 0 | I8: =1-H8-G8 -> 0.029641319 | J8: =+G8*$C8 -> 13.585022 | K8: =+H8*$C8 -> 0 | L8: =+I8*$C8 -> 0.41497846 | M8: =J8*$B8 -> 32604.052 | N8: =K8*$B8 -> 0 | O8: =L8*$B8 -> 995.94831 | P8: LIMPIEZA DE TERRENO MANUAL | Q8: 46183 | R8: 46196 | T8: =S8*D8 -> 0 | U8: C-100 | V8: =M8*$S8 -> 0 | W8: =N8*$S8 -> 0 | X8: =O8*$S8 -> 0
A9: Activity 5 | B9: 6000 | C9: 14 | D9: =B9*C9 -> 84000 | E9: C-100 | F9: Cost account 1 | G9: 0.36508 | H9: 0.57142667 | I9: =1-H9-G9 -> 0.063493329 | J9: =+G9*$C9 -> 5.11112 | K9: =+H9*$C9 -> 7.9999734 | L9: =+I9*$C9 -> 0.88890661 | M9: =J9*$B9 -> 30666.72 | N9: =K9*$B9 -> 47999.841 | O9: =L9*$B9 -> 5333.4396 | P9: TRAZO Y REPLANTEO INICIALES DEL PROYECTO | Q9: 46197 | R9: 46210 | T9: =S9*D9 -> 0 | U9: C-100 | V9: =M9*$S9 -> 0 | W9: =N9*$S9 -> 0 | X9: =O9*$S9 -> 0
A10: WBS 3 | P10: MOVIMIENTO DE TIERRAS | Q10: 46211 | R10: 46280
A11: Activity 6 | B11: 14000 | C11: 12 | D11: =B11*C11 -> 168000 | E11: C-200 | F11: Cost account 2 | G11: 0.39676091 | H11: 0 | I11: =1-H11-G11 -> 0.60323909 | J11: =+G11*$C11 -> 4.7611309 | K11: =+H11*$C11 -> 0 | L11: =+I11*$C11 -> 7.2388691 | M11: =J11*$B11 -> 66655.833 | N11: =K11*$B11 -> 0 | O11: =L11*$B11 -> 101344.17 | P11: EXCAVACION MASIVA CON MAQUINA | Q11: 46211 | R11: 46231 | T11: =S11*D11 -> 0 | U11: C-200 | V11: =M11*$S11 -> 0 | W11: =N11*$S11 -> 0 | X11: =O11*$S11 -> 0
A12: Activity 7 | B12: 8000 | C12: 35 | D12: =B12*C12 -> 280000 | E12: C-200 | F12: Cost account 2 | G12: 0.75426613 | H12: 0.011289022 | I12: =1-H12-G12 -> 0.23444484 | J12: =+G12*$C12 -> 26.399315 | K12: =+H12*$C12 -> 0.39511576 | L12: =+I12*$C12 -> 8.2055696 | M12: =J12*$B12 -> 211194.52 | N12: =K12*$B12 -> 3160.9261 | O12: =L12*$B12 -> 65644.557 | P12: RELLENO COMPACTADO CON MATERIAL PROPIO | Q12: 46260 | R12: 46273 | T12: =S12*D12 -> 0 | U12: C-200 | V12: =M12*$S12 -> 0 | W12: =N12*$S12 -> 0 | X12: =O12*$S12 -> 0
A13: Activity 8 | B13: 750 | C13: 70 | D13: =B13*C13 -> 52500 | E13: C-200 | F13: Cost account 2 | G13: 0.4185597 | H13: 0.45134089 | I13: =1-H13-G13 -> 0.13009941 | J13: =+G13*$C13 -> 29.299179 | K13: =+H13*$C13 -> 31.593862 | L13: =+I13*$C13 -> 9.1069587 | M13: =J13*$B13 -> 21974.384 | N13: =K13*$B13 -> 23695.397 | O13: =L13*$B13 -> 6830.219 | P13: RELLENO COMPACTADO CON MATERIAL DE PRESTAMO | Q13: 46260 | R13: 46280 | T13: =S13*D13 -> 0 | U13: C-200 | V13: =M13*$S13 -> 0 | W13: =N13*$S13 -> 0 | X13: =O13*$S13 -> 0
A14: WBS 4 | J14: =+G14*$C14 -> 0 | K14: =+H14*$C14 -> 0 | L14: =+I14*$C14 -> 0 | P14: CONCRETO SIMPLE
A15: WBS 4.1 | P15: SOLADO PARA ZAPATAS
A16: Activity 9 | B16: 200 | C16: 25 | D16: =B16*C16 -> 5000 | E16: C-300 | F16: Cost account 3 | G16: 0.61149691 | H16: 0.3121142 | I16: =1-H16-G16 -> 0.076388889 | J16: =+G16*$C16 -> 15.287423 | K16: =+H16*$C16 -> 7.8028549 | L16: =+I16*$C16 -> 1.9097222 | M16: =J16*$B16 -> 3057.4846 | N16: =K16*$B16 -> 1560.571 | O16: =L16*$B16 -> 381.94444 | P16: SOLADO DE CONCRETO PARA ZAPATAS MEZCLA 1:12 (e=2") | Q16: 46232 | R16: 46238 | T16: =S16*D16 -> 0 | U16: C-300 | V16: =M16*$S16 -> 0 | W16: =N16*$S16 -> 0 | X16: =O16*$S16 -> 0
A17: WBS 4.2 | J17: =+G17*$C17 -> 0 | K17: =+H17*$C17 -> 0 | L17: =+I17*$C17 -> 0 | P17: MUROS DE CONTENCION
A18: Activity 10 | B18: 5000 | C18: 45 | D18: =B18*C18 -> 225000 | E18: C-400 | F18: Cost account 4 | G18: 0.50890577 | H18: 0.47582688 | I18: =1-H18-G18 -> 0.015267354 | J18: =+G18*$C18 -> 22.90076 | K18: =+H18*$C18 -> 21.41221 | L18: =+I18*$C18 -> 0.68703092 | M18: =J18*$B18 -> 114503.8 | N18: =K18*$B18 -> 107061.05 | O18: =L18*$B18 -> 3435.1546 | P18: ENCOFRADO Y DESENCOFRADO NORMAL PARA MUROS DE CONTENCION_x000D_ | Q18: 46239 | R18: 46252 | T18: =S18*D18 -> 0 | U18: C-400 | V18: =M18*$S18 -> 0 | W18: =N18*$S18 -> 0 | X18: =O18*$S18 -> 0
A19: Activity 11 | B19: 750 | C19: 50 | D19: =B19*C19 -> 37500 | E19: C-400 | F19: Cost account 4 | G19: 0.55436702 | H19: 0.42899487 | I19: =1-H19-G19 -> 0.016638114 | J19: =+G19*$C19 -> 27.718351 | K19: =+H19*$C19 -> 21.449744 | L19: =+I19*$C19 -> 0.83190569 | M19: =J19*$B19 -> 20788.763 | N19: =K19*$B19 -> 16087.308 | O19: =L19*$B19 -> 623.92927 | P19: ENCOFRADO Y DESENCOFRADO NORMAL EN ZAPATAS DE MURO | Q19: 46239 | R19: 46245 | T19: =S19*D19 -> 0 | U19: C-400 | V19: =M19*$S19 -> 0 | W19: =N19*$S19 -> 0 | X19: =O19*$S19 -> 0
A20: Activity 12 | B20: 1100 | C20: 55 | D20: =B20*C20 -> 60500 | E20: C-300 | F20: Cost account 3 | G20: 0.52107693 | H20: 0.42884379 | I20: =1-H20-G20 -> 0.050079279 | J20: =+G20*$C20 -> 28.659231 | K20: =+H20*$C20 -> 23.586409 | L20: =+I20*$C20 -> 2.7543604 | M20: =J20*$B20 -> 31525.154 | N20: =K20*$B20 -> 25945.049 | O20: =L20*$B20 -> 3029.7964 | P20: CONCRETO CICLOPEO 30%PM PARA MUROS f'c=140 kg/m2 | Q20: 46253 | R20: 46259 | T20: =S20*D20 -> 0 | U20: C-300 | V20: =M20*$S20 -> 0 | W20: =N20*$S20 -> 0 | X20: =O20*$S20 -> 0
D22: =SUM(D4:D20) -> 1126100 | M22: =SUM(M4:M20) -> 532970.71 | N22: =SUM(N4:N20) -> 355510.14 | O22: =SUM(O4:O20) -> 237619.16 | P22: =SUM(M22:O22) -> 1126100 | T22: =SUM(T4:T20) -> 118000 | V22: =SUM(V4:V20) -> 0 | W22: =SUM(W4:W20) -> 99000 | X22: =SUM(X4:X20) -> 19000

Sheet Estructura de Control
C3: Code CA | D3: LABOUR C | E3: MATERIAL C | F3: EQUIPMENT C
C4: C-100 | D4: 492 | E4: 2490 | F4: 498
C5: C-200 | D5: 12465 | E5: 14825 | F5: 9460
C6: C-300 | D6: 1674 | E6: 1570 | F6: 3306
C7: C-400 | D7: 7500 | E7: 11125 | F7: 7625
C8: Total general | D8: 22131 | E8: 30010 | F8: 20889 | G8: =SUM(D8:F8) -> 73030
C23: Code CA | D23: Suma de Labour | E23: Suma de Mat | F23: Suma de Eq.
C24: C-100 | D24: 246 | E24: 2145 | F24: 249 | U24: Code CA | V24: Category | W24: EV | X24: AC | Y24: CV | Z24: Profit
C25: C-200 | D25: 3116.25 | E25: 3706.25 | F25: 2365 | U25: C-100 | V25: Labour | W25: 246 | X25: 150 | Y25: =+W25-X25 -> 96
C26: C-300 | D26: 424.5 | E26: 400 | F26: 938 | U26: C-200 | V26: Labour | W26: 3116.25 | X26: 2500 | Y26: =+W26-X26 -> 616.25
C27: C-400 | D27: 1875 | E27: 2781.25 | F27: 1906.25 | U27: C-300 | V27: Labour | W27: 424.5 | X27: 400 | Y27: =+W27-X27 -> 24.5
C28: Total general | D28: 5661.75 | E28: 9032.5 | F28: 5458.25 | U28: C-400 | V28: Labour | W28: 1875 | X28: 2500 | Y28: =+W28-X28 -> -625
U29: C-100 | V29: Material | W29: 2145 | X29: 1500 | Y29: =+W29-X29 -> 645
U30: C-200 | V30: Material | W30: 3706.25 | X30: 4500 | Y30: =+W30-X30 -> -793.75
U31: C-300 | V31: Material | W31: 400 | X31: 1000 | Y31: =+W31-X31 -> -600
U32: C-400 | V32: Material | W32: 2781.25 | X32: 3500 | Y32: =+W32-X32 -> -718.75
U33: C-100 | V33: Equipment | W33: 249 | X33: 200 | Y33: =+W33-X33 -> 49
U34: C-200 | V34: Equipment | W34: 2365 | X34: 2400 | Y34: =+W34-X34 -> -35
U35: C-300 | V35: Equipment | W35: 938 | X35: 900 | Y35: =+W35-X35 -> 38
U36: C-400 | V36: Equipment | W36: 1906.25 | X36: 2300 | Y36: =+W36-X36 -> -393.75
U37: Subtotal | W37: =+SUM(W25:W36) -> 20152.5 | X37: =+SUM(X25:X36) -> 21850 | Y37: =+W37-X37 -> -1697.5
U38: Overhead | W38: =+W37*0.1 -> 2015.25 | X38: 2185
U39: Subtotal 2 | W39: =+W38+W37 -> 22167.75 | X39: =+X38+X37 -> 24035
U40: Another concepts to claim | W40: 3500
D41: EV | J41: AC | O41: GAP | U41: Total | W41: =+W40+W39 -> 25667.75 | X41: =+X40+X39 -> 24035 | Y41: =+W41-X41 -> 1632.75 | Z41: =+Y41/W41 -> 0.063610951
C42: Code CA | D42: Labour | E42: Material | F42: Equipment | G42: Subtotal 1 | I42: Code CA | J42: Labour | K42: Material | L42: Equipment | M42: Subtotal 2 | O42: Labour | P42: Material | Q42: Equipment | R42: Subtotal 2
C43: C-100 | D43: 246 | E43: 2145 | F43: 249 | G43: =SUM(Tabla1[[#This Row],[Labour]:[Equipment]]) -> 2640 | I43: C-100 | J43: 150 | K43: 1500 | L43: 200 | M43: =SUM(Tabla2[[#This Row],[Labour]:[Equipment]]) -> 1850 | O43: =Tabla1[[#This Row],[Labour]]-Tabla2[[#This Row],[Labour]] -> 96 | P43: =Tabla1[[#This Row],[Material]]-Tabla2[[#This Row],[Material]] -> 645 | Q43: =Tabla1[[#This Row],[Equipment]]-Tabla2[[#This Row],[Equipment]] -> 49 | R43: =Tabla1[[#This Row],[Subtotal 1]]-Tabla2[[#This Row],[Subtotal 2]] -> 790
C44: C-200 | D44: 3116.25 | E44: 3706.25 | F44: 2365 | G44: =SUM(Tabla1[[#This Row],[Labour]:[Equipment]]) -> 9187.5 | I44: C-200 | J44: 2500 | K44: 4500 | L44: 2400 | M44: =SUM(Tabla2[[#This Row],[Labour]:[Equipment]]) -> 9400 | O44: =Tabla1[[#This Row],[Labour]]-Tabla2[[#This Row],[Labour]] -> 616.25 | P44: =Tabla1[[#This Row],[Material]]-Tabla2[[#This Row],[Material]] -> -793.75 | Q44: =Tabla1[[#This Row],[Equipment]]-Tabla2[[#This Row],[Equipment]] -> -35 | R44: =Tabla1[[#This Row],[Subtotal 1]]-Tabla2[[#This Row],[Subtotal 2]] -> -212.5
C45: C-300 | D45: 424.5 | E45: 400 | F45: 938 | G45: =SUM(Tabla1[[#This Row],[Labour]:[Equipment]]) -> 1762.5 | I45: C-300 | J45: 400 | K45: 1000 | L45: 900 | M45: =SUM(Tabla2[[#This Row],[Labour]:[Equipment]]) -> 2300 | O45: =Tabla1[[#This Row],[Labour]]-Tabla2[[#This Row],[Labour]] -> 24.5 | P45: =Tabla1[[#This Row],[Material]]-Tabla2[[#This Row],[Material]] -> -600 | Q45: =Tabla1[[#This Row],[Equipment]]-Tabla2[[#This Row],[Equipment]] -> 38 | R45: =Tabla1[[#This Row],[Subtotal 1]]-Tabla2[[#This Row],[Subtotal 2]] -> -537.5
C46: C-400 | D46: 1875 | E46: 2781.25 | F46: 1906.25 | G46: =SUM(Tabla1[[#This Row],[Labour]:[Equipment]]) -> 6562.5 | I46: C-400 | J46: 2500 | K46: 3500 | L46: 2300 | M46: =SUM(Tabla2[[#This Row],[Labour]:[Equipment]]) -> 8300 | O46: =Tabla1[[#This Row],[Labour]]-Tabla2[[#This Row],[Labour]] -> -625 | P46: =Tabla1[[#This Row],[Material]]-Tabla2[[#This Row],[Material]] -> -718.75 | Q46: =Tabla1[[#This Row],[Equipment]]-Tabla2[[#This Row],[Equipment]] -> -393.75 | R46: =Tabla1[[#This Row],[Subtotal 1]]-Tabla2[[#This Row],[Subtotal 2]] -> -1737.5
D47: =SUM(Tabla1[Labour]) -> 5661.75 | E47: =SUM(Tabla1[Material]) -> 9032.5 | F47: =SUM(Tabla1[Equipment]) -> 5458.25 | G47: =SUM(G43:G46) -> 20152.5 | J47: =SUM(Tabla2[Labour]) -> 5550 | K47: =SUM(Tabla2[Material]) -> 10500 | L47: =SUM(Tabla2[Equipment]) -> 5800 | M47: =SUM(Tabla2[Subtotal 2]) -> 21850 | O47: =SUM(O43:O46) -> 111.75 | P47: =SUM(P43:P46) -> -1467.5 | Q47: =SUM(Q43:Q46) -> -341.75 | R47: =SUM(R43:R46) -> -1697.5
C51: Code CA | D51: Description CA | E51: Support Gap | F51: Actions to implement
C52: C-100 | D52: Cost account 1 | E52: Explanation one | F52: Actions to implement one.
C53: C-200 | D53: Cost account 2 | E53: Explanation two | F53: Actions to implement two.
C54: C-300 | D54: Cost account 3 | E54: Explanation three | F54: Actions to implement three.
C55: C-400 | D55: Cost account 4 | E55: Explanation four | F55: Actions to implement four.

Sheet CV reconciliation
B3: Valuation | C3: =+(C4+C5)*1.1 -> 25850
B4: Request for payment | C4: 20000 | D4: 111730.65
B5: Accruals | C5: 3500 | D5: 5000
B7: Cost | C7: Budgeted Cost | D7: Actual Cost | E7: Gap
B8: Labour | C8: ='Estructura de Control'!D47 -> 5661.75 | D8: ='Estructura de Control'!J47 -> 5550 | E8: =+C8-D8 -> 111.75
B9: Material | C9: ='Estructura de Control'!E47 -> 9032.5 | D9: ='Estructura de Control'!K47 -> 10500 | E9: =+C9-D9 -> -1467.5
B10: Equipment | C10: ='Estructura de Control'!F47 -> 5458.25 | D10: ='Estructura de Control'!L47 -> 5800 | E10: =+C10-D10 -> -341.75
B12: GG =0.1*CD | C12: =0.1*SUM(C8:C11) -> 2015.25 | D12: =0.1*SUM(D8:D11) -> 2185 | E12: =0.1*SUM(E8:E11) -> -169.75
B13: SUB TOTAL | C13: =SUM(C8:C12) -> 22167.75 | D13: =SUM(D8:D12) -> 24035 | E13: =SUM(E8:E12) -> -1867.25
C15: Profit | D15: =+$C3-D13 -> 1815
C17: Profit | D17: =+D15/C3 -> 0.070212766
C19: EV' | D19: =C3 -> 25850
C20: AC | D20: =D13 -> 24035
C21: CPI | D21: =D19/D20 -> 1.0755149

Sheet Budgett
A3: Code | B3: Suma de Cost
A4: C-100 | B4: 3480
A5: C-200 | B5: 36750
A6: C-300 | B6: 6550
A7: C-400 | B7: 26250
A8: (en blanco)
A9: Total general | B9: 73030

Sheet P6
A1: WBS | B1: Activity ID | C1: Activity Name | D1: Planned Start | E1: Planned Finish | F1: COA | G1: Original Duration | H1: Budget
A2: RO_01 RO_Sample | D2: 46148 | E2: 46280 | G2: 95
A3: RO_01.1 WBS 1 | D3: 46148 | E3: 46182 | G3: 25
A4: RO_01.1 | B4: A1000 | C4: Activity 1 | D4: 46148 | E4: 46168 | F4: Cost account 1 | G4: 15 | H4: 80000
A5: RO_01.1 | B5: A1010 | C5: Activity 2 | D5: 46169 | E5: 46182 | F5: Cost account 1 | G5: 10 | H5: 50000
A6: RO_01.1 | B6: A1020 | C6: Activity 3 | D6: 46169 | E6: 46182 | F6: Cost account 1 | G6: 10 | H6: 50000
A7: RO_01.2 WBS 2 | D7: 46183 | E7: 46210 | G7: 20
A8: RO_01.2 | B8: A1030 | C8: Activity 4 | D8: 46183 | E8: 46196 | F8: Cost account 1 | G8: 10 | H8: 33600
A9: RO_01.2 | B9: A1040 | C9: Activity 5 | D9: 46197 | E9: 46210 | F9: Cost account 1 | G9: 10 | H9: 84000
A10: RO_01.3 WBS 3 | D10: 46211 | E10: 46280 | G10: 50
A11: RO_01.3 | B11: A1050 | C11: Activity 6 | D11: 46211 | E11: 46231 | F11: Cost account 2 | G11: 15 | H11: 168000
A12: RO_01.3 | B12: A1060 | C12: Activity 7 | D12: 46260 | E12: 46273 | F12: Cost account 2 | G12: 10 | H12: 280000
A13: RO_01.3 | B13: A1070 | C13: Activity 8 | D13: 46260 | E13: 46280 | F13: Cost account 2 | G13: 15 | H13: 52500
A14: RO_01.4 WBS4 | D14: 46232 | E14: 46259 | G14: 20
A15: RO_01.4.1 WBS 4.1 | D15: 46232 | E15: 46238 | G15: 5
A16: RO_01.4.1 | B16: A1080 | C16: Activity 9 | D16: 46232 | E16: 46238 | F16: Cost account 3 | G16: 5 | H16: 5000
A17: RO_01.4.2 WBS 4. 2 | D17: 46239 | E17: 46259 | G17: 15
A18: RO_01.4.2 | B18: A1090 | C18: Activity 10 | D18: 46239 | E18: 46252 | F18: Cost account 4 | G18: 10 | H18: 225000
A19: RO_01.4.2 | B19: A1100 | C19: Activity 11 | D19: 46239 | E19: 46245 | F19: Cost account 4 | G19: 5 | H19: 37500
A20: RO_01.4.2 | B20: A1110 | C20: Activity 12 | D20: 46253 | E20: 46259 | F20: Cost account 3 | G20: 5 | H20: 60500

Sheet Activtiy Progress
A1: Cost account | B1: Activity | C1: Unit | D1: Quantity | E1: Budget | F1: Start | G1: Finish | H1: Actual qty | I1: EV | J1: EV (Cost account) | K1: AC | L1: ETC | M1: EAC
A2: Cost account 1 | J2: =+SUM(I3:I7) -> 118000 | K2: =+J2*1.08 -> 127440 | L2: =+M2-K2 -> 179088 | M2: =SUM(E3:E7)*1.03 -> 306528
A3: Cost account 1 | B3: Activity 1 | C3: % | D3: 1 | E3: 80000 | F3: 46148 | G3: 46168 | H3: 1 | I3: =+H3*E3 -> 80000
A4: Cost account 1 | B4: Activity 2 | C4: % | D4: 1 | E4: 50000 | F4: 46169 | G4: 46182 | H4: 0.38 | I4: =+H4*E4 -> 19000
A5: Cost account 1 | B5: Activity 3 | C5: % | D5: 1 | E5: 50000 | F5: 46169 | G5: 46182 | H5: 0.38 | I5: =+H5*E5 -> 19000
A6: Cost account 1 | B6: Activity 4 | C6: m2 | D6: 2400 | E6: 33600 | F6: 46183 | G6: 46196
A7: Cost account 1 | B7: Activity 5 | C7: m2 | D7: 6000 | E7: 84000 | F7: 46197 | G7: 46210
A8: Cost account 2 | J8: 0 | K8: 0 | L8: =+M8-K8 -> 520520 | M8: =+SUM(E9:E11)*1.04 -> 520520
A9: Cost account 2 | B9: Activity 6 | C9: m3 | D9: 14000 | E9: 168000 | F9: 46211 | G9: 46231
A10: Cost account 2 | B10: Activity 7 | C10: m3 | D10: 8000 | E10: 280000 | F10: 46260 | G10: 46273
A11: Cost account 2 | B11: Activity 8 | C11: m3 | D11: 750 | E11: 52500 | F11: 46260 | G11: 46280
A12: Cost account 3 | J12: 0 | K12: 0 | L12: =+M12-K12 -> 70100 | M12: 70100
A13: Cost account 3 | B13: Activity 12 | C13: m3 | D13: 1100 | E13: 60500 | F13: 46253 | G13: 46259
A14: Cost account 3 | B14: Activity 9 | C14: m2 | D14: 200 | E14: 5000 | F14: 46232 | G14: 46238
A15: Cost account 4 | J15: 0 | K15: 0 | L15: =+M15-K15 -> 273000 | M15: =+SUM(E16:E18)*1.04 -> 273000
A16: Cost account 4 | B16: Activity 10 | C16: m2 | D16: 5000 | E16: 225000 | F16: 46239 | G16: 46252
A17: Cost account 4 | B17: Activity 11 | C17: m3 | D17: 750 | E17: 37500 | F17: 46239 | G17: 46245

Sheet Activtiy Progress_2
A1: Cost account | B1: Activity | C1: Unit | D1: Quantity | E1: Budget | F1: Start | G1: Finish | H1: Actual qty | I1: EV | J1: EV (Cost account) | K1: AC | L1: ETC | M1: EAC
A2: Cost account 1 | J2: =+SUM(I3:I7) -> 222000 | K2: =+J2*1.08 -> 239760 | L2: =+M2-K2 -> 66768 | M2: =SUM(E3:E7)*1.03 -> 306528
A3: Cost account 1 | B3: Activity 1 | C3: % | D3: 1 | E3: 80000 | F3: 46148 | G3: 46168 | H3: 1 | I3: =+H3*E3 -> 80000
A4: Cost account 1 | B4: Activity 2 | C4: % | D4: 1 | E4: 50000 | F4: 46169 | G4: 46182 | H4: 1 | I4: =+H4*E4 -> 50000
A5: Cost account 1 | B5: Activity 3 | C5: % | D5: 1 | E5: 50000 | F5: 46169 | G5: 46182 | H5: 1 | I5: =+H5*E5 -> 50000
A6: Cost account 1 | B6: Activity 4 | C6: m2 | D6: 2400 | E6: 33600 | F6: 46183 | G6: 46196 | H6: 1 | I6: =+H6*E6 -> 33600
A7: Cost account 1 | B7: Activity 5 | C7: m2 | D7: 6000 | E7: 84000 | F7: 46197 | G7: 46210 | H7: 0.1 | I7: =+H7*E7 -> 8400
A8: Cost account 2 | J8: 0 | K8: 0 | L8: =+M8-K8 -> 520520 | M8: =+SUM(E9:E11)*1.04 -> 520520
A9: Cost account 2 | B9: Activity 6 | C9: m3 | D9: 14000 | E9: 168000 | F9: 46211 | G9: 46231
A10: Cost account 2 | B10: Activity 7 | C10: m3 | D10: 8000 | E10: 280000 | F10: 46260 | G10: 46273
A11: Cost account 2 | B11: Activity 8 | C11: m3 | D11: 750 | E11: 52500 | F11: 46260 | G11: 46280
A12: Cost account 3 | J12: 0 | K12: 0 | L12: =+M12-K12 -> 70100 | M12: 70100
A13: Cost account 3 | B13: Activity 12 | C13: m3 | D13: 1100 | E13: 60500 | F13: 46253 | G13: 46259
A14: Cost account 3 | B14: Activity 9 | C14: m2 | D14: 200 | E14: 5000 | F14: 46232 | G14: 46238
A15: Cost account 4 | J15: 0 | K15: 0 | L15: =+M15-K15 -> 273000 | M15: =+SUM(E16:E18)*1.04 -> 273000
A16: Cost account 4 | B16: Activity 10 | C16: m2 | D16: 5000 | E16: 225000 | F16: 46239 | G16: 46252
A17: Cost account 4 | B17: Activity 11 | C17: m3 | D17: 750 | E17: 37500 | F17: 46239 | G17: 46245

Sheet EVM
A1: Period | B1: Variable | C1: Value | E1: Period | F1: EV | G1: AC | H1: PV | I1: PV cum
A2: 46027 | B2: EV | C2: 118000 | E2: may-26 | F2: 118000 | G2: 127440 | H2: 118462 | I2: 118462
A3: 46027 | B3: AC | C3: 127440 | E3: jun-26 | H3: 133907 | I3: =+H3+I2 -> 252369
A4: 46027 | B4: PV | C4: 118462 | E4: jul-26 | H4: 214898 | I4: =+H4+I3 -> 467267
A5: 46028 | B5: PV | C5: 133907 | E5: aug-26 | H5: 447150 | I5: =+H5+I4 -> 914417
A6: 46029 | B6: PV | C6: 214898 | E6: sep-26 | H6: 211683 | I6: =+H6+I5 -> 1126100
A7: 46030 | B7: PV | C7: 447150
A8: 46031 | B8: PV | C8: 211683
D16: CA | E16: CA2 | F16: EV | G16: AC | H16: PV | I16: CV | J16: SV | K16: CPI | L16: SPI
D17: C-100 | E17: Cost account 1 | F17: 118000 | G17: 127440 | H17: 118462 | I17: =+F17-G17 -> -9440 | J17: =+F17-H17 -> -462 | K17: =+F17/G17 -> 0.92592593 | L17: =+F17/H17 -> 0.99610002
D18: C-200 | E18: Cost account 2
D19: C-300 | E19: Cost account 3
D20: C-400 | E20: Cost account 4

Sheet EAC
A1: Cost account 3
A2: Resource name | B2: Type | C2: Unit | D2: Qty to date | E2: Unit rate TD | F2: Cost to date | G2: Qty to Complete | H2: Unit rate TC | I2: Cost to compelte
A3: Resource 1 | B3: Labor | C3: HH | D3: 0 | F3: 0 | G3: 50 | H3: 180 | I3: =+G3*H3 -> 9000
A4: Resource 2 | B4: Labor | C4: HH | D4: 0 | F4: 0 | G4: 50 | H4: 185 | I4: =+G4*H4 -> 9250
A5: Resource 3 | B5: Labor | C5: HH | D5: 0 | F5: 0 | G5: 50 | H5: 185 | I5: =+G5*H5 -> 9250
A6: Resource 4 | B6: Material | C6: m3 | D6: 0 | F6: 0 | G6: 370 | H6: 65 | I6: =+G6*H6 -> 24050
A7: Resource 5 | B7: Material | C7: m2 | D7: 0 | F7: 0 | G7: 380 | H7: 20 | I7: =+G7*H7 -> 7600
A8: Resource 6 | B8: Material | C8: ea | D8: 0 | F8: 0 | G8: 60 | H8: 2.5 | I8: =+G8*H8 -> 150
A9: Resource 7 | B9: Material | C9: ea | D9: 0 | F9: 0 | G9: 50 | H9: 2.5 | I9: =+G9*H9 -> 125
A10: Resource 8 | B10: Material | C10: ea | D10: 0 | F10: 0 | G10: 50 | H10: 3.5 | I10: =+G10*H10 -> 175
A11: Resource 9 | B11: Plant | C11: Day | D11: 0 | F11: 0 | G11: 5 | H11: 1500 | I11: =+G11*H11 -> 7500
A12: Resource 10 | B12: Plant | C12: Day | D12: 0 | F12: 0 | G12: 2 | H12: 1500 | I12: =+G12*H12 -> 3000
F13: =SUM(F3:F12) -> 0 | I13: =SUM(I3:I12) -> 70100
